rdhyee_test.py
rdhyee_test-0.1.5.dist-info/LICENSE
rdhyee_test-0.1.5.dist-info/WHEEL
rdhyee_test-0.1.5.dist-info/METADATA
rdhyee_test-0.1.5.dist-info/RECORD
