Metadata-Version: 2.1
Name: rdhyee_test
Version: 0.1.5
Summary: An amazing sample package for rdhyee to test stuff
Author-email: Raymond Yee <raymond.yee@gmail.com>
Classifier: License :: OSI Approved :: MIT License
Project-URL: Home, https://raymondyee.net
